{
  "title": "Family Computer Best Collection Vol.3",
  "titles_alternative": [
    "\u30d5\u30a1\u30df\u30b3\u30f3 \u30d9\u30b9\u30c8\u30b3\u30ec\u30af\u30b7\u30e7\u30f3 Vol.3"
  ],
  "crawled_at": "2023-09-21T23:06:52.227721+00:00",
  "slug": "family-computer-best-collection-vol.3-2006",
  "url": "https://downloads.khinsider.com/game-soundtracks/album/family-computer-best-collection-vol.3-2006",
  "platforms": {
    "Family Computer": "https://downloads.khinsider.com/game-soundtracks/family-computer",
    "NES": "https://downloads.khinsider.com/game-soundtracks/nintendo-nes"
  },
  "images": [
    "https://vgmsite.com/soundtracks/family-computer-best-collection-vol.3-2006/FCBC3%20a.jpg"
  ],
  "year": 2006,
  "catalog_number": "EZCD-0014",
  "date_added": "2023-09-17T00:00:00+00:00",
  "developers": {},
  "publishers": {
    "EtlanZ": "https://downloads.khinsider.com/game-soundtracks/publisher/etlanz"
  },
  "genres": {
    "Arrangement": "https://downloads.khinsider.com/game-soundtracks/arrangements"
  },
  "tracks": [
    {
      "disc_number": null,
      "filesize_flac_bytes": null,
      "filesize_mp3_bytes": 482344,
      "track_number": 1,
      "title": "Title BGM [Xevious]",
      "runtime": 9,
      "source_mp3": "https://vgmsite.com/soundtracks/family-computer-best-collection-vol.3-2006/vuoaeolady/01.%20Title%20BGM%20%5BXevious%5D.mp3",
      "track_url": "https://downloads.khinsider.com/game-soundtracks/album/family-computer-best-collection-vol.3-2006/01.%2520Title%2520BGM%2520%255BXevious%255D.mp3"
    },
    {
      "disc_number": null,
      "filesize_flac_bytes": null,
      "filesize_mp3_bytes": 3229614,
      "track_number": 2,
      "title": "Main Theme [Ikki]",
      "runtime": 78,
      "source_mp3": "https://vgmsite.com/soundtracks/family-computer-best-collection-vol.3-2006/fmqtnfwyll/02.%20Main%20Theme%20%5BIkki%5D.mp3",
      "track_url": "https://downloads.khinsider.com/game-soundtracks/album/family-computer-best-collection-vol.3-2006/02.%2520Main%2520Theme%2520%255BIkki%255D.mp3"
    },
    {
      "disc_number": null,
      "filesize_flac_bytes": null,
      "filesize_mp3_bytes": 3303014,
      "track_number": 3,
      "title": "Main Theme [Chubby Cherub]",
      "runtime": 79,
      "source_mp3": "https://vgmsite.com/soundtracks/family-computer-best-collection-vol.3-2006/hmtxnppxkq/03.%20Main%20Theme%20%5BChubby%20Cherub%5D.mp3",
      "track_url": "https://downloads.khinsider.com/game-soundtracks/album/family-computer-best-collection-vol.3-2006/03.%2520Main%2520Theme%2520%255BChubby%2520Cherub%255D.mp3"
    },
    {
      "disc_number": null,
      "filesize_flac_bytes": null,
      "filesize_mp3_bytes": 3565158,
      "track_number": 4,
      "title": "Main Theme+\u03b1 [Mighty Bomb Jack]",
      "runtime": 86,
      "source_mp3": "https://vgmsite.com/soundtracks/family-computer-best-collection-vol.3-2006/ssshoxvjwa/04.%20Main%20Theme%2B%CE%B1%20%5BMighty%20Bomb%20Jack%5D.mp3",
      "track_url": "https://downloads.khinsider.com/game-soundtracks/album/family-computer-best-collection-vol.3-2006/04.%2520Main%2520Theme%252B%25CE%25B1%2520%255BMighty%2520Bomb%2520Jack%255D.mp3"
    },
    {
      "disc_number": null,
      "filesize_flac_bytes": null,
      "filesize_mp3_bytes": 4760535,
      "track_number": 5,
      "title": "Helicopter Landing ~ Assault Main Theme [Commando]",
      "runtime": 116,
      "source_mp3": "https://vgmsite.com/soundtracks/family-computer-best-collection-vol.3-2006/utjvwhvcju/05.%20Helicopter%20Landing%20~%20Assault%20Main%20Theme%20%5BCommando%5D.mp3",
      "track_url": "https://downloads.khinsider.com/game-soundtracks/album/family-computer-best-collection-vol.3-2006/05.%2520Helicopter%2520Landing%2520~%2520Assault%2520Main%2520Theme%2520%255BCommando%255D.mp3"
    },
    {
      "disc_number": null,
      "filesize_flac_bytes": null,
      "filesize_mp3_bytes": 5138022,
      "track_number": 6,
      "title": "Start ~ Stage 1 [Mad\u016bra no Tsubasa]",
      "runtime": 125,
      "source_mp3": "https://vgmsite.com/soundtracks/family-computer-best-collection-vol.3-2006/xbzyfhztrl/06.%20Start%20~%20Stage%201%20%5BMad%C5%ABra%20no%20Tsubasa%5D.mp3",
      "track_url": "https://downloads.khinsider.com/game-soundtracks/album/family-computer-best-collection-vol.3-2006/06.%2520Start%2520~%2520Stage%25201%2520%255BMad%25C5%25ABra%2520no%2520Tsubasa%255D.mp3"
    },
    {
      "disc_number": null,
      "filesize_flac_bytes": null,
      "filesize_mp3_bytes": 5651824,
      "track_number": 7,
      "title": "Main Theme (Wing Mounting Time) Battle Wings",
      "runtime": 138,
      "source_mp3": "https://vgmsite.com/soundtracks/family-computer-best-collection-vol.3-2006/ofmasexgba/07.%20Main%20Theme%20%28Wing%20Mounting%20Time%29%20Battle%20Wings.mp3",
      "track_url": "https://downloads.khinsider.com/game-soundtracks/album/family-computer-best-collection-vol.3-2006/07.%2520Main%2520Theme%2520%2528Wing%2520Mounting%2520Time%2529%2520Battle%2520Wings.mp3"
    },
    {
      "disc_number": null,
      "filesize_flac_bytes": null,
      "filesize_mp3_bytes": 5861539,
      "track_number": 8,
      "title": "The Next World [Hi no Tori - Hououhen Gaou no Bouken]",
      "runtime": 143,
      "source_mp3": "https://vgmsite.com/soundtracks/family-computer-best-collection-vol.3-2006/cwlfjeeono/08.%20The%20Next%20World%20%5BHi%20no%20Tori%20-%20Hououhen%20Gaou%20no%20Bouken%5D.mp3",
      "track_url": "https://downloads.khinsider.com/game-soundtracks/album/family-computer-best-collection-vol.3-2006/08.%2520The%2520Next%2520World%2520%255BHi%2520no%2520Tori%2520-%2520Hououhen%2520Gaou%2520no%2520Bouken%255D.mp3"
    },
    {
      "disc_number": null,
      "filesize_flac_bytes": null,
      "filesize_mp3_bytes": 6815744,
      "track_number": 9,
      "title": "Chapter 4 [Famicom Mukashibanashi - Shin Onigashima]",
      "runtime": 167,
      "source_mp3": "https://vgmsite.com/soundtracks/family-computer-best-collection-vol.3-2006/qmuaqwwkjg/09.%20Chapter%204%20%5BFamicom%20Mukashibanashi%20-%20Shin%20Onigashima%5D.mp3",
      "track_url": "https://downloads.khinsider.com/game-soundtracks/album/family-computer-best-collection-vol.3-2006/09.%2520Chapter%25204%2520%255BFamicom%2520Mukashibanashi%2520-%2520Shin%2520Onigashima%255D.mp3"
    },
    {
      "disc_number": null,
      "filesize_flac_bytes": null,
      "filesize_mp3_bytes": 4949278,
      "track_number": 10,
      "title": "Theme of Autumn [Hanjuku Hero]",
      "runtime": 121,
      "source_mp3": "https://vgmsite.com/soundtracks/family-computer-best-collection-vol.3-2006/mgagqzokxz/10.%20Theme%20of%20Autumn%20%5BHanjuku%20Hero%5D.mp3",
      "track_url": "https://downloads.khinsider.com/game-soundtracks/album/family-computer-best-collection-vol.3-2006/10.%2520Theme%2520of%2520Autumn%2520%255BHanjuku%2520Hero%255D.mp3"
    },
    {
      "disc_number": null,
      "filesize_flac_bytes": null,
      "filesize_mp3_bytes": 6218055,
      "track_number": 11,
      "title": "Sunset Valley Stage [Rygar]",
      "runtime": 152,
      "source_mp3": "https://vgmsite.com/soundtracks/family-computer-best-collection-vol.3-2006/ekthpdfkle/11.%20Sunset%20Valley%20Stage%20%5BRygar%5D.mp3",
      "track_url": "https://downloads.khinsider.com/game-soundtracks/album/family-computer-best-collection-vol.3-2006/11.%2520Sunset%2520Valley%2520Stage%2520%255BRygar%255D.mp3"
    },
    {
      "disc_number": null,
      "filesize_flac_bytes": null,
      "filesize_mp3_bytes": 4938792,
      "track_number": 12,
      "title": "Words of Prayer (Password) [Faxanadu]",
      "runtime": 120,
      "source_mp3": "https://vgmsite.com/soundtracks/family-computer-best-collection-vol.3-2006/mllnnexnka/12.%20Words%20of%20Prayer%20%28Password%29%20%5BFaxanadu%5D.mp3",
      "track_url": "https://downloads.khinsider.com/game-soundtracks/album/family-computer-best-collection-vol.3-2006/12.%2520Words%2520of%2520Prayer%2520%2528Password%2529%2520%255BFaxanadu%255D.mp3"
    },
    {
      "disc_number": null,
      "filesize_flac_bytes": null,
      "filesize_mp3_bytes": 3491758,
      "track_number": 13,
      "title": "Shikoku - Hokkaido [Ganbare Goemon 2]",
      "runtime": 84,
      "source_mp3": "https://vgmsite.com/soundtracks/family-computer-best-collection-vol.3-2006/kngalkmtur/13.%20Shikoku%20-%20Hokkaido%20%5BGanbare%20Goemon%202%5D.mp3",
      "track_url": "https://downloads.khinsider.com/game-soundtracks/album/family-computer-best-collection-vol.3-2006/13.%2520Shikoku%2520-%2520Hokkaido%2520%255BGanbare%2520Goemon%25202%255D.mp3"
    },
    {
      "disc_number": null,
      "filesize_flac_bytes": null,
      "filesize_mp3_bytes": 5473566,
      "track_number": 14,
      "title": "Field [Little Ninja Brothers]",
      "runtime": 134,
      "source_mp3": "https://vgmsite.com/soundtracks/family-computer-best-collection-vol.3-2006/euibisanci/14.%20Field%20%5BLittle%20Ninja%20Brothers%5D.mp3",
      "track_url": "https://downloads.khinsider.com/game-soundtracks/album/family-computer-best-collection-vol.3-2006/14.%2520Field%2520%255BLittle%2520Ninja%2520Brothers%255D.mp3"
    },
    {
      "disc_number": null,
      "filesize_flac_bytes": null,
      "filesize_mp3_bytes": 3932160,
      "track_number": 15,
      "title": "The Depths of the Earth Stage [Doraemon - Giga Zombie no Gyakush\u016b]",
      "runtime": 95,
      "source_mp3": "https://vgmsite.com/soundtracks/family-computer-best-collection-vol.3-2006/aengbqplbh/15.%20The%20Depths%20of%20the%20Earth%20Stage%20%5BDoraemon%20-%20Giga%20Zombie%20no%20Gyakush%C5%AB%5D.mp3",
      "track_url": "https://downloads.khinsider.com/game-soundtracks/album/family-computer-best-collection-vol.3-2006/15.%2520The%2520Depths%2520of%2520the%2520Earth%2520Stage%2520%255BDoraemon%2520-%2520Giga%2520Zombie%2520no%2520Gyakush%25C5%25AB%255D.mp3"
    },
    {
      "disc_number": null,
      "filesize_flac_bytes": null,
      "filesize_mp3_bytes": 4875878,
      "track_number": 16,
      "title": "Resturant Stage (STAGE1) [Mendel Palace]",
      "runtime": 119,
      "source_mp3": "https://vgmsite.com/soundtracks/family-computer-best-collection-vol.3-2006/lcuckjsisq/16.%20Resturant%20Stage%20%28STAGE1%29%20%5BMendel%20Palace%5D.mp3",
      "track_url": "https://downloads.khinsider.com/game-soundtracks/album/family-computer-best-collection-vol.3-2006/16.%2520Resturant%2520Stage%2520%2528STAGE1%2529%2520%255BMendel%2520Palace%255D.mp3"
    },
    {
      "disc_number": null,
      "filesize_flac_bytes": null,
      "filesize_mp3_bytes": 4246732,
      "track_number": 17,
      "title": "Crossing the Great Ocean [Heracles no Eik\u014d II - Taitan no Metsub\u014d]",
      "runtime": 103,
      "source_mp3": "https://vgmsite.com/soundtracks/family-computer-best-collection-vol.3-2006/adeezlxbch/17.%20Crossing%20the%20Great%20Ocean%20%5BHeracles%20no%20Eik%C5%8D%20II%20-%20Taitan%20no%20Metsub%C5%8D%5D.mp3",
      "track_url": "https://downloads.khinsider.com/game-soundtracks/album/family-computer-best-collection-vol.3-2006/17.%2520Crossing%2520the%2520Great%2520Ocean%2520%255BHeracles%2520no%2520Eik%25C5%258D%2520II%2520-%2520Taitan%2520no%2520Metsub%25C5%258D%255D.mp3"
    },
    {
      "disc_number": null,
      "filesize_flac_bytes": null,
      "filesize_mp3_bytes": 6973030,
      "track_number": 18,
      "title": "Title BGM [Wizardry II - The Knight of Diamonds]",
      "runtime": 171,
      "source_mp3": "https://vgmsite.com/soundtracks/family-computer-best-collection-vol.3-2006/jreegvvfvs/18.%20Title%20BGM%20%5BWizardry%20II%20-%20The%20Knight%20of%20Diamonds%5D.mp3",
      "track_url": "https://downloads.khinsider.com/game-soundtracks/album/family-computer-best-collection-vol.3-2006/18.%2520Title%2520BGM%2520%255BWizardry%2520II%2520-%2520The%2520Knight%2520of%2520Diamonds%255D.mp3"
    },
    {
      "disc_number": null,
      "filesize_flac_bytes": null,
      "filesize_mp3_bytes": 6920601,
      "track_number": 19,
      "title": "Hallucination ~ Hellish Illusions[Digital Devil Story - Megami Tensei II]",
      "runtime": 170,
      "source_mp3": "https://vgmsite.com/soundtracks/family-computer-best-collection-vol.3-2006/kcdlduponv/19.%20Hallucination%20~%20Hellish%20Illusions%5BDigital%20Devil%20Story%20-%20Megami%20Tensei%20II%5D.mp3",
      "track_url": "https://downloads.khinsider.com/game-soundtracks/album/family-computer-best-collection-vol.3-2006/19.%2520Hallucination%2520~%2520Hellish%2520Illusions%255BDigital%2520Devil%2520Story%2520-%2520Megami%2520Tensei%2520II%255D.mp3"
    },
    {
      "disc_number": null,
      "filesize_flac_bytes": null,
      "filesize_mp3_bytes": 3439329,
      "track_number": 20,
      "title": "Last Battle (VS Sima Yi) [Destiny of an Emperor II]",
      "runtime": 83,
      "source_mp3": "https://vgmsite.com/soundtracks/family-computer-best-collection-vol.3-2006/xdjqustesi/20.%20Last%20Battle%20%28VS%20Sima%20Yi%29%20%5BDestiny%20of%20an%20Emperor%20II%5D.mp3",
      "track_url": "https://downloads.khinsider.com/game-soundtracks/album/family-computer-best-collection-vol.3-2006/20.%2520Last%2520Battle%2520%2528VS%2520Sima%2520Yi%2529%2520%255BDestiny%2520of%2520an%2520Emperor%2520II%255D.mp3"
    },
    {
      "disc_number": null,
      "filesize_flac_bytes": null,
      "filesize_mp3_bytes": 4645191,
      "track_number": 21,
      "title": "Main Theme+\u03b1 [Tower of Druaga]",
      "runtime": 113,
      "source_mp3": "https://vgmsite.com/soundtracks/family-computer-best-collection-vol.3-2006/ytlkfiffqz/21.%20Main%20Theme%2B%CE%B1%20%5BTower%20of%20Druaga%5D.mp3",
      "track_url": "https://downloads.khinsider.com/game-soundtracks/album/family-computer-best-collection-vol.3-2006/21.%2520Main%2520Theme%252B%25CE%25B1%2520%255BTower%2520of%2520Druaga%255D.mp3"
    },
    {
      "disc_number": null,
      "filesize_flac_bytes": null,
      "filesize_mp3_bytes": 6406799,
      "track_number": 22,
      "title": "Cross Country [Downtown Nekketsu Koushinkyoku - Soreyuke Daiundoukai]",
      "runtime": 157,
      "source_mp3": "https://vgmsite.com/soundtracks/family-computer-best-collection-vol.3-2006/kfzsyxomou/22.%20Cross%20Country%20%5BDowntown%20Nekketsu%20Koushinkyoku%20-%20Soreyuke%20Daiundoukai%5D.mp3",
      "track_url": "https://downloads.khinsider.com/game-soundtracks/album/family-computer-best-collection-vol.3-2006/22.%2520Cross%2520Country%2520%255BDowntown%2520Nekketsu%2520Koushinkyoku%2520-%2520Soreyuke%2520Daiundoukai%255D.mp3"
    },
    {
      "disc_number": null,
      "filesize_flac_bytes": null,
      "filesize_mp3_bytes": 9059696,
      "track_number": 23,
      "title": "Obstacle Room [Downtown Nekketsu Koushinkyoku - Soreyuke Daiundoukai]",
      "runtime": 223,
      "source_mp3": "https://vgmsite.com/soundtracks/family-computer-best-collection-vol.3-2006/oigxzanpwn/23.%20Obstacle%20Room%20%5BDowntown%20Nekketsu%20Koushinkyoku%20-%20Soreyuke%20Daiundoukai%5D.mp3",
      "track_url": "https://downloads.khinsider.com/game-soundtracks/album/family-computer-best-collection-vol.3-2006/23.%2520Obstacle%2520Room%2520%255BDowntown%2520Nekketsu%2520Koushinkyoku%2520-%2520Soreyuke%2520Daiundoukai%255D.mp3"
    },
    {
      "disc_number": null,
      "filesize_flac_bytes": null,
      "filesize_mp3_bytes": 6889144,
      "track_number": 24,
      "title": "Damawari Game [Downtown Nekketsu Koushinkyoku - Soreyuke Daiundoukai]",
      "runtime": 169,
      "source_mp3": "https://vgmsite.com/soundtracks/family-computer-best-collection-vol.3-2006/amvatsynnj/24.%20Damawari%20Game%20%5BDowntown%20Nekketsu%20Koushinkyoku%20-%20Soreyuke%20Daiundoukai%5D.mp3",
      "track_url": "https://downloads.khinsider.com/game-soundtracks/album/family-computer-best-collection-vol.3-2006/24.%2520Damawari%2520Game%2520%255BDowntown%2520Nekketsu%2520Koushinkyoku%2520-%2520Soreyuke%2520Daiundoukai%255D.mp3"
    },
    {
      "disc_number": null,
      "filesize_flac_bytes": null,
      "filesize_mp3_bytes": 6018826,
      "track_number": 25,
      "title": "Kachimaki Hand-to-hand Fighting [Downtown Nekketsu Koushinkyoku - Soreyuke Daiundoukai]",
      "runtime": 147,
      "source_mp3": "https://vgmsite.com/soundtracks/family-computer-best-collection-vol.3-2006/rtckgomrcn/25.%20Kachimaki%20Hand-to-hand%20Fighting%20%5BDowntown%20Nekketsu%20Koushinkyoku%20-%20Soreyuke%20Daiundoukai%5D.mp3",
      "track_url": "https://downloads.khinsider.com/game-soundtracks/album/family-computer-best-collection-vol.3-2006/25.%2520Kachimaki%2520Hand-to-hand%2520Fighting%2520%255BDowntown%2520Nekketsu%2520Koushinkyoku%2520-%2520Soreyuke%2520Daiundoukai%255D.mp3"
    },
    {
      "disc_number": null,
      "filesize_flac_bytes": null,
      "filesize_mp3_bytes": 4624220,
      "track_number": 26,
      "title": "Main Theme+\u03b1 [Ninja Jajamaru-kun]",
      "runtime": 113,
      "source_mp3": "https://vgmsite.com/soundtracks/family-computer-best-collection-vol.3-2006/lbwtfxcfsv/26.%20Main%20Theme%2B%CE%B1%20%5BNinja%20Jajamaru-kun%5D.mp3",
      "track_url": "https://downloads.khinsider.com/game-soundtracks/album/family-computer-best-collection-vol.3-2006/26.%2520Main%2520Theme%252B%25CE%25B1%2520%255BNinja%2520Jajamaru-kun%255D.mp3"
    }
  ],
  "total": {
    "runtime": 3215,
    "filesize_mp3_bytes": 131910849,
    "filesize_flac_bytes": 0,
    "tracks": 26
  }
}