{
  "title": "Honor of Kings Original Game Soundtrack Vol. 2",
  "titles_alternative": [
    "Honor of Kings (Original Game Soundtrack), Vol. 2"
  ],
  "crawled_at": "2023-09-22T12:48:39.160308+00:00",
  "slug": "honor-of-kings-original-game-soundtrack-vol.-2-2021",
  "url": "https://downloads.khinsider.com/game-soundtracks/album/honor-of-kings-original-game-soundtrack-vol.-2-2021",
  "platforms": {
    "Android": "https://downloads.khinsider.com/game-soundtracks/android",
    "iOS": "https://downloads.khinsider.com/game-soundtracks/ios"
  },
  "images": [
    "https://vgmsite.com/soundtracks/honor-of-kings-original-game-soundtrack-vol.-2-2021/coverart.jpg"
  ],
  "year": 2021,
  "catalog_number": null,
  "date_added": "2023-08-17T00:00:00+00:00",
  "developers": {
    "Unisonar": "https://downloads.khinsider.com/game-soundtracks/developer/unisonar"
  },
  "publishers": {},
  "genres": {
    "Soundtrack": "https://downloads.khinsider.com/game-soundtracks/ost"
  },
  "tracks": [
    {
      "disc_number": null,
      "filesize_flac_bytes": 29286727,
      "filesize_mp3_bytes": 9237954,
      "track_number": 1,
      "title": "Breath of Nature",
      "runtime": 274,
      "source_mp3": "https://vgmsite.com/soundtracks/honor-of-kings-original-game-soundtrack-vol.-2-2021/sgxbgqqthn/01.%20Breath%20of%20Nature.mp3",
      "source_flac": "https://vgmsite.com/soundtracks/honor-of-kings-original-game-soundtrack-vol.-2-2021/sgxbgqqthn/01.%20Breath%20of%20Nature.flac",
      "track_url": "https://downloads.khinsider.com/game-soundtracks/album/honor-of-kings-original-game-soundtrack-vol.-2-2021/01.%2520Breath%2520of%2520Nature.mp3"
    },
    {
      "disc_number": null,
      "filesize_flac_bytes": 19377684,
      "filesize_mp3_bytes": 6165626,
      "track_number": 2,
      "title": "Dream or Memory",
      "runtime": 185,
      "source_mp3": "https://vgmsite.com/soundtracks/honor-of-kings-original-game-soundtrack-vol.-2-2021/irwekyvfny/02.%20Dream%20or%20Memory.mp3",
      "source_flac": "https://vgmsite.com/soundtracks/honor-of-kings-original-game-soundtrack-vol.-2-2021/irwekyvfny/02.%20Dream%20or%20Memory.flac",
      "track_url": "https://downloads.khinsider.com/game-soundtracks/album/honor-of-kings-original-game-soundtrack-vol.-2-2021/02.%2520Dream%2520or%2520Memory.mp3"
    },
    {
      "disc_number": null,
      "filesize_flac_bytes": 16263413,
      "filesize_mp3_bytes": 5756682,
      "track_number": 3,
      "title": "Floating Dreams",
      "runtime": 187,
      "source_mp3": "https://vgmsite.com/soundtracks/honor-of-kings-original-game-soundtrack-vol.-2-2021/okogxfiued/03.%20Floating%20Dreams.mp3",
      "source_flac": "https://vgmsite.com/soundtracks/honor-of-kings-original-game-soundtrack-vol.-2-2021/okogxfiued/03.%20Floating%20Dreams.flac",
      "track_url": "https://downloads.khinsider.com/game-soundtracks/album/honor-of-kings-original-game-soundtrack-vol.-2-2021/03.%2520Floating%2520Dreams.mp3"
    },
    {
      "disc_number": null,
      "filesize_flac_bytes": 19042140,
      "filesize_mp3_bytes": 6186598,
      "track_number": 4,
      "title": "Journey of a Thousand Troops",
      "runtime": 184,
      "source_mp3": "https://vgmsite.com/soundtracks/honor-of-kings-original-game-soundtrack-vol.-2-2021/latwgyeewz/04.%20Journey%20of%20a%20Thousand%20Troops.mp3",
      "source_flac": "https://vgmsite.com/soundtracks/honor-of-kings-original-game-soundtrack-vol.-2-2021/latwgyeewz/04.%20Journey%20of%20a%20Thousand%20Troops.flac",
      "track_url": "https://downloads.khinsider.com/game-soundtracks/album/honor-of-kings-original-game-soundtrack-vol.-2-2021/04.%2520Journey%2520of%2520a%2520Thousand%2520Troops.mp3"
    },
    {
      "disc_number": null,
      "filesize_flac_bytes": 21548236,
      "filesize_mp3_bytes": 6627000,
      "track_number": 5,
      "title": "Legend of Xuanyong",
      "runtime": 193,
      "source_mp3": "https://vgmsite.com/soundtracks/honor-of-kings-original-game-soundtrack-vol.-2-2021/gippfvymdm/05.%20Legend%20of%20Xuanyong.mp3",
      "source_flac": "https://vgmsite.com/soundtracks/honor-of-kings-original-game-soundtrack-vol.-2-2021/gippfvymdm/05.%20Legend%20of%20Xuanyong.flac",
      "track_url": "https://downloads.khinsider.com/game-soundtracks/album/honor-of-kings-original-game-soundtrack-vol.-2-2021/05.%2520Legend%2520of%2520Xuanyong.mp3"
    },
    {
      "disc_number": null,
      "filesize_flac_bytes": 20227031,
      "filesize_mp3_bytes": 6710886,
      "track_number": 6,
      "title": "The Assassin",
      "runtime": 193,
      "source_mp3": "https://vgmsite.com/soundtracks/honor-of-kings-original-game-soundtrack-vol.-2-2021/legeofyuju/06.%20The%20Assassin.mp3",
      "source_flac": "https://vgmsite.com/soundtracks/honor-of-kings-original-game-soundtrack-vol.-2-2021/legeofyuju/06.%20The%20Assassin.flac",
      "track_url": "https://downloads.khinsider.com/game-soundtracks/album/honor-of-kings-original-game-soundtrack-vol.-2-2021/06.%2520The%2520Assassin.mp3"
    },
    {
      "disc_number": null,
      "filesize_flac_bytes": 18937282,
      "filesize_mp3_bytes": 6480199,
      "track_number": 7,
      "title": "Chasing Shadows",
      "runtime": 193,
      "source_mp3": "https://vgmsite.com/soundtracks/honor-of-kings-original-game-soundtrack-vol.-2-2021/xuvbcceigz/07.%20Chasing%20Shadows.mp3",
      "source_flac": "https://vgmsite.com/soundtracks/honor-of-kings-original-game-soundtrack-vol.-2-2021/xuvbcceigz/07.%20Chasing%20Shadows.flac",
      "track_url": "https://downloads.khinsider.com/game-soundtracks/album/honor-of-kings-original-game-soundtrack-vol.-2-2021/07.%2520Chasing%2520Shadows.mp3"
    },
    {
      "disc_number": null,
      "filesize_flac_bytes": 20363345,
      "filesize_mp3_bytes": 6448742,
      "track_number": 8,
      "title": "Overture of Mengyan",
      "runtime": 187,
      "source_mp3": "https://vgmsite.com/soundtracks/honor-of-kings-original-game-soundtrack-vol.-2-2021/rdsnrjqmkr/08.%20Overture%20of%20Mengyan.mp3",
      "source_flac": "https://vgmsite.com/soundtracks/honor-of-kings-original-game-soundtrack-vol.-2-2021/rdsnrjqmkr/08.%20Overture%20of%20Mengyan.flac",
      "track_url": "https://downloads.khinsider.com/game-soundtracks/album/honor-of-kings-original-game-soundtrack-vol.-2-2021/08.%2520Overture%2520of%2520Mengyan.mp3"
    },
    {
      "disc_number": null,
      "filesize_flac_bytes": 21757952,
      "filesize_mp3_bytes": 6983516,
      "track_number": 9,
      "title": "The Academy",
      "runtime": 203,
      "source_mp3": "https://vgmsite.com/soundtracks/honor-of-kings-original-game-soundtrack-vol.-2-2021/pgadcgjdfu/09.%20The%20Academy.mp3",
      "source_flac": "https://vgmsite.com/soundtracks/honor-of-kings-original-game-soundtrack-vol.-2-2021/pgadcgjdfu/09.%20The%20Academy.flac",
      "track_url": "https://downloads.khinsider.com/game-soundtracks/album/honor-of-kings-original-game-soundtrack-vol.-2-2021/09.%2520The%2520Academy.mp3"
    },
    {
      "disc_number": null,
      "filesize_flac_bytes": 27504148,
      "filesize_mp3_bytes": 8545894,
      "track_number": 10,
      "title": "Awakening of the Warrior",
      "runtime": 251,
      "source_mp3": "https://vgmsite.com/soundtracks/honor-of-kings-original-game-soundtrack-vol.-2-2021/iwbmwrkdek/10.%20Awakening%20of%20the%20Warrior.mp3",
      "source_flac": "https://vgmsite.com/soundtracks/honor-of-kings-original-game-soundtrack-vol.-2-2021/iwbmwrkdek/10.%20Awakening%20of%20the%20Warrior.flac",
      "track_url": "https://downloads.khinsider.com/game-soundtracks/album/honor-of-kings-original-game-soundtrack-vol.-2-2021/10.%2520Awakening%2520of%2520the%2520Warrior.mp3"
    },
    {
      "disc_number": null,
      "filesize_flac_bytes": 24326963,
      "filesize_mp3_bytes": 7644119,
      "track_number": 11,
      "title": "Admiral Leng",
      "runtime": 224,
      "source_mp3": "https://vgmsite.com/soundtracks/honor-of-kings-original-game-soundtrack-vol.-2-2021/ccweytrxoy/11.%20Admiral%20Leng.mp3",
      "source_flac": "https://vgmsite.com/soundtracks/honor-of-kings-original-game-soundtrack-vol.-2-2021/ccweytrxoy/11.%20Admiral%20Leng.flac",
      "track_url": "https://downloads.khinsider.com/game-soundtracks/album/honor-of-kings-original-game-soundtrack-vol.-2-2021/11.%2520Admiral%2520Leng.mp3"
    },
    {
      "disc_number": null,
      "filesize_flac_bytes": 20929576,
      "filesize_mp3_bytes": 6585057,
      "track_number": 12,
      "title": "Chariot of War",
      "runtime": 190,
      "source_mp3": "https://vgmsite.com/soundtracks/honor-of-kings-original-game-soundtrack-vol.-2-2021/zdyephvydp/12.%20Chariot%20of%20War.mp3",
      "source_flac": "https://vgmsite.com/soundtracks/honor-of-kings-original-game-soundtrack-vol.-2-2021/zdyephvydp/12.%20Chariot%20of%20War.flac",
      "track_url": "https://downloads.khinsider.com/game-soundtracks/album/honor-of-kings-original-game-soundtrack-vol.-2-2021/12.%2520Chariot%2520of%2520War.mp3"
    },
    {
      "disc_number": null,
      "filesize_flac_bytes": 19000197,
      "filesize_mp3_bytes": 6469713,
      "track_number": 13,
      "title": "Rivers of Arrows",
      "runtime": 188,
      "source_mp3": "https://vgmsite.com/soundtracks/honor-of-kings-original-game-soundtrack-vol.-2-2021/pdvjpycstg/13.%20Rivers%20of%20Arrows.mp3",
      "source_flac": "https://vgmsite.com/soundtracks/honor-of-kings-original-game-soundtrack-vol.-2-2021/pdvjpycstg/13.%20Rivers%20of%20Arrows.flac",
      "track_url": "https://downloads.khinsider.com/game-soundtracks/album/honor-of-kings-original-game-soundtrack-vol.-2-2021/13.%2520Rivers%2520of%2520Arrows.mp3"
    },
    {
      "disc_number": null,
      "filesize_flac_bytes": 17710448,
      "filesize_mp3_bytes": 5872025,
      "track_number": 14,
      "title": "A Thousand Hills",
      "runtime": 183,
      "source_mp3": "https://vgmsite.com/soundtracks/honor-of-kings-original-game-soundtrack-vol.-2-2021/qinqvicltu/14.%20A%20Thousand%20Hills.mp3",
      "source_flac": "https://vgmsite.com/soundtracks/honor-of-kings-original-game-soundtrack-vol.-2-2021/qinqvicltu/14.%20A%20Thousand%20Hills.flac",
      "track_url": "https://downloads.khinsider.com/game-soundtracks/album/honor-of-kings-original-game-soundtrack-vol.-2-2021/14.%2520A%2520Thousand%2520Hills.mp3"
    },
    {
      "disc_number": null,
      "filesize_flac_bytes": 20248002,
      "filesize_mp3_bytes": 6616514,
      "track_number": 15,
      "title": "Flame of the Frontier",
      "runtime": 187,
      "source_mp3": "https://vgmsite.com/soundtracks/honor-of-kings-original-game-soundtrack-vol.-2-2021/xwpznnqcrp/15.%20Flame%20of%20the%20Frontier.mp3",
      "source_flac": "https://vgmsite.com/soundtracks/honor-of-kings-original-game-soundtrack-vol.-2-2021/xwpznnqcrp/15.%20Flame%20of%20the%20Frontier.flac",
      "track_url": "https://downloads.khinsider.com/game-soundtracks/album/honor-of-kings-original-game-soundtrack-vol.-2-2021/15.%2520Flame%2520of%2520the%2520Frontier.mp3"
    },
    {
      "disc_number": null,
      "filesize_flac_bytes": 19639828,
      "filesize_mp3_bytes": 6333399,
      "track_number": 16,
      "title": "The Guardians Return",
      "runtime": 179,
      "source_mp3": "https://vgmsite.com/soundtracks/honor-of-kings-original-game-soundtrack-vol.-2-2021/igqgvwfmmx/16.%20The%20Guardians%20Return.mp3",
      "source_flac": "https://vgmsite.com/soundtracks/honor-of-kings-original-game-soundtrack-vol.-2-2021/igqgvwfmmx/16.%20The%20Guardians%20Return.flac",
      "track_url": "https://downloads.khinsider.com/game-soundtracks/album/honor-of-kings-original-game-soundtrack-vol.-2-2021/16.%2520The%2520Guardians%2520Return.mp3"
    }
  ],
  "total": {
    "runtime": 3201,
    "filesize_mp3_bytes": 108663924,
    "filesize_flac_bytes": 336162972,
    "tracks": 16
  }
}