{
  "title": "NASCAR Rumble",
  "titles_alternative": [],
  "crawled_at": "2023-09-23T12:41:25.641506+00:00",
  "slug": "nascar-rumble-ps1-gamerip-2000",
  "url": "https://downloads.khinsider.com/game-soundtracks/album/nascar-rumble-ps1-gamerip-2000",
  "platforms": {
    "PS1": "https://downloads.khinsider.com/game-soundtracks/playstation"
  },
  "images": [
    "https://vgmsite.com/soundtracks/nascar-rumble-ps1-gamerip-2000/image_2023-04-01_171307042.png"
  ],
  "year": 2000,
  "date_added": "2023-04-05T00:00:00+00:00",
  "developers": {
    "Electronic Arts": "https://downloads.khinsider.com/game-soundtracks/developer/electronic-arts",
    "Visceral Games": "https://downloads.khinsider.com/game-soundtracks/developer/visceral-games"
  },
  "publishers": {
    "Electronic Arts": "https://downloads.khinsider.com/game-soundtracks/publisher/electronic-arts"
  },
  "genres": {
    "Gamerip": "https://downloads.khinsider.com/game-soundtracks/gamerips"
  },
  "tracks": [
    {
      "disc_number": null,
      "filesize_flac_bytes": null,
      "filesize_mp3_bytes": 2778726,
      "track_number": 1,
      "title": "Beach Blast",
      "runtime": 173,
      "source_mp3": "https://vgmsite.com/soundtracks/nascar-rumble-ps1-gamerip-2000/uzytwsfmzv/01.%20Beach%20Blast.mp3",
      "track_url": "https://downloads.khinsider.com/game-soundtracks/album/nascar-rumble-ps1-gamerip-2000/01.%2520Beach%2520Blast.mp3"
    },
    {
      "disc_number": null,
      "filesize_flac_bytes": null,
      "filesize_mp3_bytes": 3177185,
      "track_number": 2,
      "title": "Bad Lands",
      "runtime": 158,
      "source_mp3": "https://vgmsite.com/soundtracks/nascar-rumble-ps1-gamerip-2000/zuhhwngyvg/02.%20Bad%20Lands.mp3",
      "track_url": "https://downloads.khinsider.com/game-soundtracks/album/nascar-rumble-ps1-gamerip-2000/02.%2520Bad%2520Lands.mp3"
    },
    {
      "disc_number": null,
      "filesize_flac_bytes": null,
      "filesize_mp3_bytes": 2998927,
      "track_number": 3,
      "title": "Bonus",
      "runtime": 187,
      "source_mp3": "https://vgmsite.com/soundtracks/nascar-rumble-ps1-gamerip-2000/jtlighzfpk/03.%20Bonus.mp3",
      "track_url": "https://downloads.khinsider.com/game-soundtracks/album/nascar-rumble-ps1-gamerip-2000/03.%2520Bonus.mp3"
    },
    {
      "disc_number": null,
      "filesize_flac_bytes": null,
      "filesize_mp3_bytes": 1300234,
      "track_number": 4,
      "title": "Credits",
      "runtime": 80,
      "source_mp3": "https://vgmsite.com/soundtracks/nascar-rumble-ps1-gamerip-2000/magwnqoeyu/04.%20Credits.mp3",
      "track_url": "https://downloads.khinsider.com/game-soundtracks/album/nascar-rumble-ps1-gamerip-2000/04.%2520Credits.mp3"
    },
    {
      "disc_number": null,
      "filesize_flac_bytes": null,
      "filesize_mp3_bytes": 4550819,
      "track_number": 5,
      "title": "Gold Rush",
      "runtime": 283,
      "source_mp3": "https://vgmsite.com/soundtracks/nascar-rumble-ps1-gamerip-2000/pvdxhyejqk/05.%20Gold%20Rush.mp3",
      "track_url": "https://downloads.khinsider.com/game-soundtracks/album/nascar-rumble-ps1-gamerip-2000/05.%2520Gold%2520Rush.mp3"
    },
    {
      "disc_number": null,
      "filesize_flac_bytes": null,
      "filesize_mp3_bytes": 3523215,
      "track_number": 6,
      "title": "Mardi Gras",
      "runtime": 219,
      "source_mp3": "https://vgmsite.com/soundtracks/nascar-rumble-ps1-gamerip-2000/xebysiejqj/06.%20Mardi%20Gras.mp3",
      "track_url": "https://downloads.khinsider.com/game-soundtracks/album/nascar-rumble-ps1-gamerip-2000/06.%2520Mardi%2520Gras.mp3"
    },
    {
      "disc_number": null,
      "filesize_flac_bytes": null,
      "filesize_mp3_bytes": 3428843,
      "track_number": 7,
      "title": "Menu",
      "runtime": 213,
      "source_mp3": "https://vgmsite.com/soundtracks/nascar-rumble-ps1-gamerip-2000/lxwemlskal/07.%20Menu.mp3",
      "track_url": "https://downloads.khinsider.com/game-soundtracks/album/nascar-rumble-ps1-gamerip-2000/07.%2520Menu.mp3"
    },
    {
      "disc_number": null,
      "filesize_flac_bytes": null,
      "filesize_mp3_bytes": 4173332,
      "track_number": 8,
      "title": "Metropolis",
      "runtime": 260,
      "source_mp3": "https://vgmsite.com/soundtracks/nascar-rumble-ps1-gamerip-2000/zrbovoyhtf/08.%20Metropolis.mp3",
      "track_url": "https://downloads.khinsider.com/game-soundtracks/album/nascar-rumble-ps1-gamerip-2000/08.%2520Metropolis.mp3"
    },
    {
      "disc_number": null,
      "filesize_flac_bytes": null,
      "filesize_mp3_bytes": 3449815,
      "track_number": 9,
      "title": "Southern Exposure",
      "runtime": 215,
      "source_mp3": "https://vgmsite.com/soundtracks/nascar-rumble-ps1-gamerip-2000/ektkhbxcbo/09.%20Southern%20Exposure.mp3",
      "track_url": "https://downloads.khinsider.com/game-soundtracks/album/nascar-rumble-ps1-gamerip-2000/09.%2520Southern%2520Exposure.mp3"
    }
  ],
  "total": {
    "runtime": 1788,
    "filesize_mp3_bytes": 29381096,
    "filesize_flac_bytes": 0,
    "tracks": 9
  }
}