{
  "title": "Ys Battle Specialinfo",
  "titles_alternative": [
    "\u30a4\u30fc\u30b9 \u30d0\u30c8\u30eb\u30fb\u30b9\u30da\u30b7\u30e3\u30eb"
  ],
  "crawled_at": "2024-02-17T00:30:01.215582+00:00",
  "slug": "ys-battle-special-2002",
  "url": "https://downloads.khinsider.com/game-soundtracks/album/ys-battle-special-2002",
  "platforms": {
    "SNES": "https://downloads.khinsider.com/game-soundtracks/nintendo-snes",
    "TurboGrafx-16": "https://downloads.khinsider.com/game-soundtracks/turbografx-16",
    "Windows": "https://downloads.khinsider.com/game-soundtracks/windows"
  },
  "images": [
    "https://vgmsite.com/soundtracks/ys-battle-special-2002/00%20Front.jpg"
  ],
  "year": 2002,
  "catalog_number": null,
  "date_added": "2024-02-09T00:00:00+00:00",
  "developers": {},
  "publishers": {},
  "genres": {
    "Arrangement": "https://downloads.khinsider.com/game-soundtracks/arrangements"
  },
  "tracks": [
    {
      "disc_number": null,
      "filesize_flac_bytes": 29905387,
      "filesize_mp3_bytes": 9300869,
      "track_number": 1,
      "title": "Termination",
      "runtime": 255,
      "source_mp3": "https://vgmsite.com/soundtracks/ys-battle-special-2002/hdwyhvdtgd/01%20Termination.mp3",
      "source_flac": "https://vgmsite.com/soundtracks/ys-battle-special-2002/hdwyhvdtgd/01%20Termination.flac",
      "track_url": "https://downloads.khinsider.com/game-soundtracks/album/ys-battle-special-2002/01%2520Termination.mp3"
    },
    {
      "disc_number": null,
      "filesize_flac_bytes": 27577548,
      "filesize_mp3_bytes": 8829009,
      "track_number": 2,
      "title": "Battle Ground",
      "runtime": 265,
      "source_mp3": "https://vgmsite.com/soundtracks/ys-battle-special-2002/chgcaiihcz/02%20Battle%20Ground.mp3",
      "source_flac": "https://vgmsite.com/soundtracks/ys-battle-special-2002/chgcaiihcz/02%20Battle%20Ground.flac",
      "track_url": "https://downloads.khinsider.com/game-soundtracks/album/ys-battle-special-2002/02%2520Battle%2520Ground.mp3"
    },
    {
      "disc_number": null,
      "filesize_flac_bytes": 42351984,
      "filesize_mp3_bytes": 11628707,
      "track_number": 3,
      "title": "The Ordeal Becomes Great",
      "runtime": 337,
      "source_mp3": "https://vgmsite.com/soundtracks/ys-battle-special-2002/lajiysadwz/03%20The%20Ordeal%20Becomes%20Great.mp3",
      "source_flac": "https://vgmsite.com/soundtracks/ys-battle-special-2002/lajiysadwz/03%20The%20Ordeal%20Becomes%20Great.flac",
      "track_url": "https://downloads.khinsider.com/game-soundtracks/album/ys-battle-special-2002/03%2520The%2520Ordeal%2520Becomes%2520Great.mp3"
    },
    {
      "disc_number": null,
      "filesize_flac_bytes": 26612858,
      "filesize_mp3_bytes": 8766095,
      "track_number": 4,
      "title": "Final Battle",
      "runtime": 266,
      "source_mp3": "https://vgmsite.com/soundtracks/ys-battle-special-2002/uywowfbgwf/04%20Final%20Battle.mp3",
      "source_flac": "https://vgmsite.com/soundtracks/ys-battle-special-2002/uywowfbgwf/04%20Final%20Battle.flac",
      "track_url": "https://downloads.khinsider.com/game-soundtracks/album/ys-battle-special-2002/04%2520Final%2520Battle.mp3"
    },
    {
      "disc_number": null,
      "filesize_flac_bytes": 27567063,
      "filesize_mp3_bytes": 8136949,
      "track_number": 5,
      "title": "Bad Species",
      "runtime": 242,
      "source_mp3": "https://vgmsite.com/soundtracks/ys-battle-special-2002/cszwgjkcto/05%20Bad%20Species.mp3",
      "source_flac": "https://vgmsite.com/soundtracks/ys-battle-special-2002/cszwgjkcto/05%20Bad%20Species.flac",
      "track_url": "https://downloads.khinsider.com/game-soundtracks/album/ys-battle-special-2002/05%2520Bad%2520Species.mp3"
    },
    {
      "disc_number": null,
      "filesize_flac_bytes": 28930211,
      "filesize_mp3_bytes": 8797552,
      "track_number": 6,
      "title": "Turning Death Spiral",
      "runtime": 247,
      "source_mp3": "https://vgmsite.com/soundtracks/ys-battle-special-2002/hnqlisfvnq/06%20Turning%20Death%20Spiral.mp3",
      "source_flac": "https://vgmsite.com/soundtracks/ys-battle-special-2002/hnqlisfvnq/06%20Turning%20Death%20Spiral.flac",
      "track_url": "https://downloads.khinsider.com/game-soundtracks/album/ys-battle-special-2002/06%2520Turning%2520Death%2520Spiral.mp3"
    },
    {
      "disc_number": null,
      "filesize_flac_bytes": 23729274,
      "filesize_mp3_bytes": 9080668,
      "track_number": 7,
      "title": "Protectors",
      "runtime": 289,
      "source_mp3": "https://vgmsite.com/soundtracks/ys-battle-special-2002/zsnaqgpucj/07%20Protectors.mp3",
      "source_flac": "https://vgmsite.com/soundtracks/ys-battle-special-2002/zsnaqgpucj/07%20Protectors.flac",
      "track_url": "https://downloads.khinsider.com/game-soundtracks/album/ys-battle-special-2002/07%2520Protectors.mp3"
    },
    {
      "disc_number": null,
      "filesize_flac_bytes": 25490882,
      "filesize_mp3_bytes": 8420065,
      "track_number": 8,
      "title": "Battle #58",
      "runtime": 250,
      "source_mp3": "https://vgmsite.com/soundtracks/ys-battle-special-2002/hbickzoyya/08%20Battle%20%2358.mp3",
      "source_flac": "https://vgmsite.com/soundtracks/ys-battle-special-2002/hbickzoyya/08%20Battle%20%2358.flac",
      "track_url": "https://downloads.khinsider.com/game-soundtracks/album/ys-battle-special-2002/08%2520Battle%2520%252358.mp3"
    },
    {
      "disc_number": null,
      "filesize_flac_bytes": 31918653,
      "filesize_mp3_bytes": 8399093,
      "track_number": 9,
      "title": "Dekakyara",
      "runtime": 249,
      "source_mp3": "https://vgmsite.com/soundtracks/ys-battle-special-2002/enfhbyikkd/09%20Dekakyara.mp3",
      "source_flac": "https://vgmsite.com/soundtracks/ys-battle-special-2002/enfhbyikkd/09%20Dekakyara.flac",
      "track_url": "https://downloads.khinsider.com/game-soundtracks/album/ys-battle-special-2002/09%2520Dekakyara.mp3"
    },
    {
      "disc_number": null,
      "filesize_flac_bytes": 33491517,
      "filesize_mp3_bytes": 10884218,
      "track_number": 10,
      "title": "Dark Beasts as Black as Night",
      "runtime": 306,
      "source_mp3": "https://vgmsite.com/soundtracks/ys-battle-special-2002/nsazyjphdb/10%20Dark%20Beasts%20as%20Black%20as%20Night.mp3",
      "source_flac": "https://vgmsite.com/soundtracks/ys-battle-special-2002/nsazyjphdb/10%20Dark%20Beasts%20as%20Black%20as%20Night.flac",
      "track_url": "https://downloads.khinsider.com/game-soundtracks/album/ys-battle-special-2002/10%2520Dark%2520Beasts%2520as%2520Black%2520as%2520Night.mp3"
    }
  ],
  "total": {
    "runtime": 2706,
    "filesize_mp3_bytes": 92243225,
    "filesize_flac_bytes": 297575377,
    "tracks": 10
  }
}